MANIFEST.in
README.rst
setup.py
ckanext/__init__.py
ckanext/semantictags/__init__.py
ckanext/semantictags/commands.py
ckanext/semantictags/controller.py
ckanext/semantictags/db.py
ckanext/semantictags/plugin.py
ckanext/semantictags/templates/package/snippets/package_basic_fields.html
ckanext/semantictags/templates/semantictags/index.html
ckanext/semantictags/templates/semantictags/predicates.html
ckanext/semantictags/templates/semantictags/semantictags.html
ckanext/semantictags/templates/semantictags/suggestions.html
ckanext/semantictags/templates/semantictags/tag_semantictags.html
ckanext/semantictags/templates/semantictags/snippets/associate_form.html
ckanext/semantictags/templates/semantictags/snippets/breadcrumb.html
ckanext/semantictags/templates/semantictags/snippets/list_predicates.html
ckanext/semantictags/templates/semantictags/snippets/list_semantictags.html
ckanext/semantictags/templates/semantictags/snippets/list_tag_semantictags.html
ckanext/semantictags/templates/semantictags/snippets/menu.html
ckanext/semantictags/templates/semantictags/snippets/predicate_form.html
ckanext/semantictags/templates/semantictags/snippets/semantictag_form.html
ckanext/semantictags/templates/snippets/tag_list.html
ckanext/semantictags/tests/__init__.py
ckanext/semantictags/tests/test_plugin.py
ckanext_semantictags.egg-info/PKG-INFO
ckanext_semantictags.egg-info/SOURCES.txt
ckanext_semantictags.egg-info/dependency_links.txt
ckanext_semantictags.egg-info/entry_points.txt
ckanext_semantictags.egg-info/top_level.txt