Metadata-Version: 1.1
Name: ckanext-semantictags
Version: 0.0.2
Summary: Associates local tags with semantic resources
Home-page: https://github.com/alantygel/ckanext-semantictags
Author: Alan Tygel
Author-email: alantygel@gmail.com
License: AGPL
Keywords: CKAN tags,LOD,semantics
Platform: UNKNOWN
Classifier: Development Status :: 4 - Beta
Classifier: License :: OSI Approved :: GNU Affero General Public License v3 or later (AGPLv3+)
Classifier: Programming Language :: Python :: 2.6
Classifier: Programming Language :: Python :: 2.7
